LICENSE
README.md
setup.py
mywish/__init__.py
mywish/deployer/__init__.py
mywish/deployer/brownie_deployer.py
mywish/deployer/common_dataclasses.py
mywish/deployer/exeptions.py
mywish/deployer/interface.py
mywish_deployer.egg-info/PKG-INFO
mywish_deployer.egg-info/SOURCES.txt
mywish_deployer.egg-info/dependency_links.txt
mywish_deployer.egg-info/not-zip-safe
mywish_deployer.egg-info/requires.txt
mywish_deployer.egg-info/top_level.txt