Metadata-Version: 2.1
Name: mywish-deployer
Version: 0.3.7
Summary: UNKNOWN
Home-page: https://github.com/MyWishPlatform/mywish_contract_deployer
License: UNKNOWN
Platform: UNKNOWN
License-File: LICENSE
